dailyrevenue/__init__.py
dailyrevenue/dailyrevenue.py
davidtesting-1.0.dist-info/METADATA
davidtesting-1.0.dist-info/WHEEL
davidtesting-1.0.dist-info/top_level.txt
davidtesting-1.0.dist-info/RECORD
